{
    "appKeys": {},
    "capabilities": [
        ""
    ],
    "companyName": "wazapc@gmail.com",
    "longName": "Tutorial 2 - Customization",
    "projectType": "native",
    "resources": {
        "media": [
            {
                "file": "images/background.png",
                "name": "IMAGE_BACKGROUND",
                "type": "png"
            },
            {
                "file": "fonts/perfect-dos-vga.ttf",
                "name": "FONT_PERFECT_DOS_48",
                "type": "font"
            }
        ]
    },
    "sdkVersion": "2",
    "shortName": "Tutorial 2 - Customization",
    "uuid": "2db94b16-659a-48cc-a406-a3527065709f",
    "versionCode": 1,
    "versionLabel": "1.0",
    "watchapp": {
        "watchface": false
    }
}
